pysoemdanfoss/__init__.py
pysoemdanfoss/pysoem.cp311-win_amd64.pyd
pysoemdanfoss-0.0.4.dist-info/licenses/LICENSE
pysoemdanfoss-0.0.4.dist-info/METADATA
pysoemdanfoss-0.0.4.dist-info/WHEEL
pysoemdanfoss-0.0.4.dist-info/top_level.txt
pysoemdanfoss-0.0.4.dist-info/RECORD
