Metadata-Version: 2.4
Name: pysoemdanfoss
Version: 0.0.4
Summary: Cython wrapper for the SOEM Library
Home-page: https://github.com/bnjmnp/pysoem
Author: Benjamin Partzsch
Author-email: benjamin_partzsch@web.de
License: MIT
Project-URL: Documentation, https://pysoem.readthedocs.io
Classifier: Development Status :: 2 - Pre-Alpha
Classifier: License :: OSI Approved :: MIT License
Classifier: Programming Language :: Python
Classifier: Programming Language :: Cython
Classifier: Programming Language :: C
Classifier: Programming Language :: Python :: 3
Classifier: Programming Language :: Python :: Implementation :: CPython
Classifier: Topic :: Scientific/Engineering
License-File: LICENSE
Dynamic: author
Dynamic: author-email
Dynamic: classifier
Dynamic: description
Dynamic: home-page
Dynamic: license
Dynamic: license-file
Dynamic: project-url
Dynamic: summary
